{
  "id": "mtggoldfish-commander",
  "name": "MTGGoldfish Commander",
  "description": "Top metagame decks from MTGGoldfish (commander)",
  "icon": "G",
  "format": "commander",
  "version": 1,
  "updated": "2026-07-04T00:00:00Z",
  "source": "https://www.mtggoldfish.com/metagame/commander",
  "decks": [
    {
      "name": "Doctor Doom, King of Latveria",
      "author": "MTGGoldfish",
      "colors": [
        "U",
        "B",
        "R"
      ],
      "tags": [
        "metagame"
      ],
      "main": [
        {
          "count": 1,
          "name": "Doctor Doom, King of Latveria"
        },
        {
          "count": 1,
          "name": "Canyon Slough"
        },
        {
          "count": 1,
          "name": "Watery Grave"
        },
        {
          "count": 1,
          "name": "Carnage, Crimson Chaos"
        },
        {
          "count": 1,
          "name": "Command Tower"
        },
        {
          "count": 1,
          "name": "Crumbling Necropolis"
        },
        {
          "count": 1,
          "name": "Dragonskull Summit"
        },
        {
          "count": 1,
          "name": "Drowned Catacomb"
        },
        {
          "count": 1,
          "name": "Exotic Orchard"
        },
        {
          "count": 1,
          "name": "Fetid Pools"
        },
        {
          "count": 1,
          "name": "Foreboding Ruins"
        },
        {
          "count": 1,
          "name": "Frostboil Snarl"
        },
        {
          "count": 4,
          "name": "Island"
        },
        {
          "count": 1,
          "name": "Luxury Suite"
        },
        {
          "count": 5,
          "name": "Mountain"
        },
        {
          "count": 1,
          "name": "Path of Ancestry"
        },
        {
          "count": 1,
          "name": "Ultron, Artificial Malevolence"
        },
        {
          "count": 1,
          "name": "Roaming Throne"
        },
        {
          "count": 1,
          "name": "Secluded Courtyard"
        },
        {
          "count": 1,
          "name": "Smoldering Marsh"
        },
        {
          "count": 1,
          "name": "Sulfur Falls"
        },
        {
          "count": 1,
          "name": "Sunken Hollow"
        },
        {
          "count": 6,
          "name": "Swamp"
        },
        {
          "count": 1,
          "name": "Doctor Doom"
        },
        {
          "count": 1,
          "name": "Unclaimed Territory"
        },
        {
          "count": 1,
          "name": "Villainous Hideout"
        },
        {
          "count": 1,
          "name": "Bedevil"
        },
        {
          "count": 1,
          "name": "Chaos Warp"
        },
        {
          "count": 1,
          "name": "Lethal Scheme"
        },
        {
          "count": 1,
          "name": "Terminate"
        },
        {
          "count": 1,
          "name": "Withering Torment"
        },
        {
          "count": 1,
          "name": "Arcane Signet"
        },
        {
          "count": 1,
          "name": "Currency Converter"
        },
        {
          "count": 1,
          "name": "Avengers: Under Siege"
        },
        {
          "count": 1,
          "name": "Doom's Time Platform"
        },
        {
          "count": 1,
          "name": "Loki's Scepter"
        },
        {
          "count": 1,
          "name": "Patchwork Banner"
        },
        {
          "count": 1,
          "name": "Progenitor's Icon"
        },
        {
          "count": 1,
          "name": "Skullclamp"
        },
        {
          "count": 1,
          "name": "Sol Ring"
        },
        {
          "count": 1,
          "name": "Swiftfoot Boots"
        },
        {
          "count": 1,
          "name": "Talisman of Dominance"
        },
        {
          "count": 1,
          "name": "Talisman of Indulgence"
        },
        {
          "count": 1,
          "name": "Abomination, World Ravager"
        },
        {
          "count": 1,
          "name": "Baron Strucker, HYDRA Overlord"
        },
        {
          "count": 1,
          "name": "Thunderbolts Conspiracy"
        },
        {
          "count": 1,
          "name": "Chameleon, Master of Disguise"
        },
        {
          "count": 1,
          "name": "Containment Construct"
        },
        {
          "count": 1,
          "name": "Steam Vents"
        },
        {
          "count": 1,
          "name": "Iron Monger, Sadistic Tycoon"
        },
        {
          "count": 1,
          "name": "Kang Prime"
        },
        {
          "count": 1,
          "name": "Kang, Temporal Tyrant"
        },
        {
          "count": 1,
          "name": "Killmonger, Ruthless Usurper"
        },
        {
          "count": 1,
          "name": "Klaw, Master of Sound"
        },
        {
          "count": 1,
          "name": "Construct a Cosmic Cube"
        },
        {
          "count": 1,
          "name": "Living Laser"
        },
        {
          "count": 1,
          "name": "Loki, the Deceiver"
        },
        {
          "count": 1,
          "name": "Madame Hydra"
        },
        {
          "count": 1,
          "name": "Molecule Man"
        },
        {
          "count": 1,
          "name": "Moonstone, Harsh Mistress"
        },
        {
          "count": 1,
          "name": "Prowler, Clawed Thief"
        },
        {
          "count": 1,
          "name": "Puppet Master, String Puller"
        },
        {
          "count": 1,
          "name": "Red Ghost, Intangible Genius"
        },
        {
          "count": 1,
          "name": "Spark Double"
        },
        {
          "count": 1,
          "name": "Stilt-Man, Towering Terror"
        },
        {
          "count": 1,
          "name": "Ares, God of War"
        },
        {
          "count": 1,
          "name": "The Frightful Four"
        },
        {
          "count": 1,
          "name": "The Squadron Sinister"
        },
        {
          "count": 1,
          "name": "Titan of Littjara"
        },
        {
          "count": 1,
          "name": "Dark Fortress"
        },
        {
          "count": 1,
          "name": "Tombstone, Career Criminal"
        },
        {
          "count": 1,
          "name": "Oscorp Industries"
        },
        {
          "count": 1,
          "name": "Typhoid Mary, Fractured"
        },
        {
          "count": 1,
          "name": "Ultron, Unlimited"
        },
        {
          "count": 1,
          "name": "Age of Ultron"
        },
        {
          "count": 1,
          "name": "Archnemesis"
        },
        {
          "count": 1,
          "name": "Black Market Connections"
        },
        {
          "count": 1,
          "name": "Glorious Purpose"
        },
        {
          "count": 1,
          "name": "Kang Dynasty"
        },
        {
          "count": 1,
          "name": "Propaganda"
        },
        {
          "count": 1,
          "name": "Blasphemous Act"
        },
        {
          "count": 1,
          "name": "Endless Ranks of HYDRA"
        },
        {
          "count": 1,
          "name": "Extract Power"
        },
        {
          "count": 1,
          "name": "Kindred Dominance"
        },
        {
          "count": 1,
          "name": "Night's Whisper"
        },
        {
          "count": 1,
          "name": "Spymaster's Vault"
        },
        {
          "count": 1,
          "name": "Toxic Deluge"
        },
        {
          "count": 1,
          "name": "Vandalblast"
        }
      ],
      "sideboard": []
    },
    {
      "name": "The Astonishing Ant-Man",
      "author": "MTGGoldfish",
      "colors": [
        "U",
        "G"
      ],
      "tags": [
        "metagame"
      ],
      "main": [
        {
          "count": 1,
          "name": "The Astonishing Ant-Man"
        },
        {
          "count": 10,
          "name": "Island"
        },
        {
          "count": 11,
          "name": "Forest"
        },
        {
          "count": 1,
          "name": "Proft's Eidetic Memory"
        },
        {
          "count": 1,
          "name": "Pensive Professor"
        },
        {
          "count": 1,
          "name": "Hardened Scales"
        },
        {
          "count": 1,
          "name": "Otawara, Soaring City"
        },
        {
          "count": 1,
          "name": "Wan Shi Tong, Librarian"
        },
        {
          "count": 1,
          "name": "Bristly Bill, Spine Sower"
        },
        {
          "count": 1,
          "name": "Ozolith, the Shattered Spire"
        },
        {
          "count": 1,
          "name": "Incubation Druid"
        },
        {
          "count": 1,
          "name": "Innkeeper's Talent"
        },
        {
          "count": 1,
          "name": "Doubling Season"
        },
        {
          "count": 1,
          "name": "Strength of Will"
        },
        {
          "count": 1,
          "name": "Mossborn Hydra"
        },
        {
          "count": 1,
          "name": "Elvish Mystic"
        },
        {
          "count": 1,
          "name": "Training Grounds"
        },
        {
          "count": 1,
          "name": "Super Intelligence"
        },
        {
          "count": 1,
          "name": "Ant-Man, Colony Commander"
        },
        {
          "count": 1,
          "name": "Command Tower"
        },
        {
          "count": 1,
          "name": "Arcane Signet"
        },
        {
          "count": 1,
          "name": "Slip Out the Back"
        },
        {
          "count": 1,
          "name": "Parallel Lives"
        },
        {
          "count": 1,
          "name": "Kami of Whispered Hopes"
        },
        {
          "count": 1,
          "name": "Brainstorm"
        },
        {
          "count": 1,
          "name": "Finale of Devastation"
        },
        {
          "count": 1,
          "name": "Opt"
        },
        {
          "count": 1,
          "name": "Rapid Hybridization"
        },
        {
          "count": 1,
          "name": "Enduring Curiosity"
        },
        {
          "count": 1,
          "name": "Counterspell"
        },
        {
          "count": 1,
          "name": "Cyclonic Rift"
        },
        {
          "count": 1,
          "name": "Negate"
        },
        {
          "count": 1,
          "name": "Spirit Water Revival"
        },
        {
          "count": 1,
          "name": "Toski, Bearer of Secrets"
        },
        {
          "count": 1,
          "name": "Deep Analysis"
        },
        {
          "count": 1,
          "name": "Quick Study"
        },
        {
          "count": 1,
          "name": "Yavimaya Coast"
        },
        {
          "count": 1,
          "name": "Delighted Halfling"
        },
        {
          "count": 1,
          "name": "Archmage's Charm"
        },
        {
          "count": 1,
          "name": "Finale of Revelation"
        },
        {
          "count": 1,
          "name": "Defend the Rider"
        },
        {
          "count": 1,
          "name": "Farseek"
        },
        {
          "count": 1,
          "name": "Heroic Intervention"
        },
        {
          "count": 1,
          "name": "Cultivate"
        },
        {
          "count": 1,
          "name": "Lessons from Life"
        },
        {
          "count": 1,
          "name": "Frantic Search"
        },
        {
          "count": 1,
          "name": "Growing Rites of Itlimoc"
        },
        {
          "count": 1,
          "name": "Enduring Vitality"
        },
        {
          "count": 1,
          "name": "Faerie Mastermind"
        },
        {
          "count": 1,
          "name": "Eureka Moment"
        },
        {
          "count": 1,
          "name": "Pym Particles"
        },
        {
          "count": 1,
          "name": "Craterhoof Behemoth"
        },
        {
          "count": 1,
          "name": "Rhystic Study"
        },
        {
          "count": 1,
          "name": "Llanowar Elves"
        },
        {
          "count": 1,
          "name": "Explore"
        },
        {
          "count": 1,
          "name": "Growth Spiral"
        },
        {
          "count": 1,
          "name": "Pawpatch Formation"
        },
        {
          "count": 1,
          "name": "Boseiju, Who Endures"
        },
        {
          "count": 1,
          "name": "Willowrush Verge"
        },
        {
          "count": 1,
          "name": "Breeding Pool"
        },
        {
          "count": 1,
          "name": "Dreamroot Cascade"
        },
        {
          "count": 1,
          "name": "Hedge Maze"
        },
        {
          "count": 1,
          "name": "Lumbering Falls"
        },
        {
          "count": 1,
          "name": "Fabled Passage"
        },
        {
          "count": 1,
          "name": "Flooded Strand"
        },
        {
          "count": 1,
          "name": "Wooded Foothills"
        },
        {
          "count": 1,
          "name": "Harmonized Trio"
        },
        {
          "count": 1,
          "name": "Archmage Emeritus"
        },
        {
          "count": 1,
          "name": "Prosperous Innkeeper"
        },
        {
          "count": 1,
          "name": "Sanctum Weaver"
        },
        {
          "count": 1,
          "name": "Kid Loki"
        },
        {
          "count": 1,
          "name": "Haywire Mite"
        },
        {
          "count": 1,
          "name": "Ouroboroid"
        },
        {
          "count": 1,
          "name": "Evendo, Waking Haven"
        },
        {
          "count": 1,
          "name": "Three Tree City"
        },
        {
          "count": 1,
          "name": "Triumph of the Hordes"
        },
        {
          "count": 1,
          "name": "Emerald Medallion"
        },
        {
          "count": 1,
          "name": "Terrasymbiosis"
        },
        {
          "count": 1,
          "name": "The Earth Crystal"
        },
        {
          "count": 1,
          "name": "Sol Ring"
        },
        {
          "count": 1,
          "name": "Sapphire Medallion"
        }
      ],
      "sideboard": []
    },
    {
      "name": "The Unbeatable Squirrel Girl",
      "author": "MTGGoldfish",
      "colors": [
        "G"
      ],
      "tags": [
        "metagame"
      ],
      "main": [
        {
          "count": 1,
          "name": "Akroma's Memorial"
        },
        {
          "count": 1,
          "name": "Altar of the Brood"
        },
        {
          "count": 1,
          "name": "Archdruid's Charm"
        },
        {
          "count": 1,
          "name": "Bala Ged Recovery"
        },
        {
          "count": 1,
          "name": "Beast Within"
        },
        {
          "count": 1,
          "name": "Beastmaster Ascension"
        },
        {
          "count": 1,
          "name": "Birds of Paradise"
        },
        {
          "count": 1,
          "name": "Boseiju, Who Endures"
        },
        {
          "count": 1,
          "name": "Broken Bond"
        },
        {
          "count": 1,
          "name": "Chord of Calling"
        },
        {
          "count": 1,
          "name": "Circle of Dreams Druid"
        },
        {
          "count": 1,
          "name": "Citanul Hierophants"
        },
        {
          "count": 1,
          "name": "Coat of Arms"
        },
        {
          "count": 1,
          "name": "Command Beacon"
        },
        {
          "count": 1,
          "name": "Concordant Crossroads"
        },
        {
          "count": 1,
          "name": "Craterhoof Behemoth"
        },
        {
          "count": 1,
          "name": "Crop Rotation"
        },
        {
          "count": 1,
          "name": "Cryptolith Rite"
        },
        {
          "count": 1,
          "name": "Cultivate"
        },
        {
          "count": 1,
          "name": "Curious Forager"
        },
        {
          "count": 1,
          "name": "Doubling Season"
        },
        {
          "count": 1,
          "name": "Earthcraft"
        },
        {
          "count": 1,
          "name": "Enduring Vitality"
        },
        {
          "count": 1,
          "name": "Evendo, Waking Haven"
        },
        {
          "count": 1,
          "name": "Expedition Map"
        },
        {
          "count": 1,
          "name": "Fabled Passage"
        },
        {
          "count": 1,
          "name": "Finale of Devastation"
        },
        {
          "count": 1,
          "name": "For the Common Good"
        },
        {
          "count": 1,
          "name": "Force of Vigor"
        },
        {
          "count": 20,
          "name": "Forest"
        },
        {
          "count": 1,
          "name": "Formidable Speaker"
        },
        {
          "count": 1,
          "name": "Gaea's Cradle"
        },
        {
          "count": 1,
          "name": "Genesis Wave"
        },
        {
          "count": 1,
          "name": "Green Sun's Zenith"
        },
        {
          "count": 1,
          "name": "Growing Rites of Itlimoc"
        },
        {
          "count": 1,
          "name": "Heritage Reclamation"
        },
        {
          "count": 1,
          "name": "Heroic Intervention"
        },
        {
          "count": 1,
          "name": "Honored Dreyleader"
        },
        {
          "count": 1,
          "name": "Ivy Lane Denizen"
        },
        {
          "count": 1,
          "name": "Jaheira, Friend of the Forest"
        },
        {
          "count": 1,
          "name": "Kodama's Reach"
        },
        {
          "count": 1,
          "name": "Krosan Grip"
        },
        {
          "count": 1,
          "name": "Lightning Greaves"
        },
        {
          "count": 1,
          "name": "Llanowar Elves"
        },
        {
          "count": 1,
          "name": "Misty Rainforest"
        },
        {
          "count": 1,
          "name": "Natural Order"
        },
        {
          "count": 1,
          "name": "Nature's Lore"
        },
        {
          "count": 1,
          "name": "Oakhollow Village"
        },
        {
          "count": 1,
          "name": "Parallel Lives"
        },
        {
          "count": 1,
          "name": "Patchwork Banner"
        },
        {
          "count": 1,
          "name": "Phyrexian Altar"
        },
        {
          "count": 1,
          "name": "Quest for Renewal"
        },
        {
          "count": 1,
          "name": "Saryth, the Viper's Fang"
        },
        {
          "count": 1,
          "name": "Scurry Oak"
        },
        {
          "count": 1,
          "name": "Scurry of Squirrels"
        },
        {
          "count": 1,
          "name": "Seedborn Muse"
        },
        {
          "count": 1,
          "name": "Shang-Chi, Master of Kung Fu"
        },
        {
          "count": 1,
          "name": "Shifting Woodland"
        },
        {
          "count": 1,
          "name": "Skullclamp"
        },
        {
          "count": 1,
          "name": "Skyshroud Claim"
        },
        {
          "count": 1,
          "name": "Sol Ring"
        },
        {
          "count": 1,
          "name": "Squirrel Mob"
        },
        {
          "count": 1,
          "name": "Squirrel Nest"
        },
        {
          "count": 1,
          "name": "Squirrel Sovereign"
        },
        {
          "count": 1,
          "name": "Staff of Domination"
        },
        {
          "count": 1,
          "name": "Swarmyard"
        },
        {
          "count": 1,
          "name": "Swiftfoot Boots"
        },
        {
          "count": 1,
          "name": "Sylvan Scrying"
        },
        {
          "count": 1,
          "name": "The One Ring"
        },
        {
          "count": 1,
          "name": "Thornvault Forager"
        },
        {
          "count": 1,
          "name": "Three Visits"
        },
        {
          "count": 1,
          "name": "Throne of the God-Pharaoh"
        },
        {
          "count": 1,
          "name": "Toski, Bearer of Secrets"
        },
        {
          "count": 1,
          "name": "Verdant Catacombs"
        },
        {
          "count": 1,
          "name": "White Lotus Tile"
        },
        {
          "count": 1,
          "name": "Wilderness Reclamation"
        },
        {
          "count": 1,
          "name": "Windswept Heath"
        },
        {
          "count": 1,
          "name": "Wooded Foothills"
        },
        {
          "count": 1,
          "name": "Worldly Tutor"
        },
        {
          "count": 1,
          "name": "Yavimaya Hollow"
        },
        {
          "count": 1,
          "name": "The Unbeatable Squirrel Girl"
        }
      ],
      "sideboard": []
    },
    {
      "name": "Tony Stark",
      "author": "MTGGoldfish",
      "colors": [
        "U",
        "R"
      ],
      "tags": [
        "metagame"
      ],
      "main": [
        {
          "count": 1,
          "name": "Fugitive Droid"
        },
        {
          "count": 1,
          "name": "Stark Industries Executive"
        },
        {
          "count": 1,
          "name": "Hawkeye, Master Marksman"
        },
        {
          "count": 1,
          "name": "Hydraulic Helper"
        },
        {
          "count": 1,
          "name": "Rescue, Pepper Potts"
        },
        {
          "count": 1,
          "name": "Shuri, Wakandan Inventor"
        },
        {
          "count": 1,
          "name": "Academy Manufactor"
        },
        {
          "count": 1,
          "name": "Iron Lad, Diverging Destiny"
        },
        {
          "count": 1,
          "name": "Iron Lad, Young Avenger"
        },
        {
          "count": 1,
          "name": "Iron Spider, Stark Upgrade"
        },
        {
          "count": 1,
          "name": "Loyal Inventor"
        },
        {
          "count": 1,
          "name": "H.E.R.B.I.E. Scout Unit"
        },
        {
          "count": 1,
          "name": "Iron Man, Master of Machines"
        },
        {
          "count": 1,
          "name": "Lyla, Holographic Assistant"
        },
        {
          "count": 1,
          "name": "The Vision"
        },
        {
          "count": 1,
          "name": "Thor, Asgard's Avenger"
        },
        {
          "count": 1,
          "name": "Urza, Lord High Artificer"
        },
        {
          "count": 1,
          "name": "Falcon, Winged Wonder"
        },
        {
          "count": 1,
          "name": "Iron Man, Bleeding Edge"
        },
        {
          "count": 1,
          "name": "Iron Man, Titan of Innovation"
        },
        {
          "count": 1,
          "name": "Ironheart, Clever Champion"
        },
        {
          "count": 1,
          "name": "Victor Timely, Wily Tycoon"
        },
        {
          "count": 1,
          "name": "Happy Hogan, Bodyguard"
        },
        {
          "count": 1,
          "name": "Kappa Cannoneer"
        },
        {
          "count": 1,
          "name": "Iron Giant"
        },
        {
          "count": 1,
          "name": "Threefold Thunderhulk"
        },
        {
          "count": 1,
          "name": "The Walls of Ba Sing Se"
        },
        {
          "count": 1,
          "name": "Vision, Spectral Synthezoid"
        },
        {
          "count": 1,
          "name": "Krang, Utrom Warlord"
        },
        {
          "count": 1,
          "name": "Galvanic Blast"
        },
        {
          "count": 1,
          "name": "Frantic Search"
        },
        {
          "count": 1,
          "name": "I Am Iron Man"
        },
        {
          "count": 1,
          "name": "Launch Mishap"
        },
        {
          "count": 1,
          "name": "Repulsor Blast"
        },
        {
          "count": 1,
          "name": "Commander's Plate"
        },
        {
          "count": 1,
          "name": "Elixir"
        },
        {
          "count": 1,
          "name": "Hawkeye's Bow"
        },
        {
          "count": 1,
          "name": "Iron Suitcase"
        },
        {
          "count": 1,
          "name": "Prying Blade"
        },
        {
          "count": 1,
          "name": "Sol Ring"
        },
        {
          "count": 1,
          "name": "Vibranium Energy Daggers"
        },
        {
          "count": 1,
          "name": "Armory of Iroas"
        },
        {
          "count": 1,
          "name": "Captain America's Shield"
        },
        {
          "count": 1,
          "name": "Dowsing Device"
        },
        {
          "count": 1,
          "name": "Falcon's Wing Harness"
        },
        {
          "count": 1,
          "name": "Futurist Forge"
        },
        {
          "count": 1,
          "name": "Improvised Arsenal"
        },
        {
          "count": 1,
          "name": "Iron Man Armor"
        },
        {
          "count": 1,
          "name": "Sculpting Steel"
        },
        {
          "count": 1,
          "name": "Whispersilk Cloak"
        },
        {
          "count": 1,
          "name": "Worn Powerstone"
        },
        {
          "count": 1,
          "name": "Hulkbuster Armor"
        },
        {
          "count": 1,
          "name": "Mjolnir, Hammer of Thor"
        },
        {
          "count": 1,
          "name": "Panther Habit"
        },
        {
          "count": 1,
          "name": "Arc Reactor"
        },
        {
          "count": 1,
          "name": "Meteoric Mace"
        },
        {
          "count": 1,
          "name": "Kaldra Compleat"
        },
        {
          "count": 1,
          "name": "Ultima Weapon"
        },
        {
          "count": 1,
          "name": "The Ten Rings"
        },
        {
          "count": 1,
          "name": "Excalibur, Sword of Eden"
        },
        {
          "count": 1,
          "name": "Armor Wars"
        },
        {
          "count": 1,
          "name": "Origin of Iron Man"
        },
        {
          "count": 1,
          "name": "Avengers Tower"
        },
        {
          "count": 1,
          "name": "Escape Tunnel"
        },
        {
          "count": 1,
          "name": "Fogwell's Gym"
        },
        {
          "count": 1,
          "name": "Inventors' Fair"
        },
        {
          "count": 14,
          "name": "Island"
        },
        {
          "count": 13,
          "name": "Mountain"
        },
        {
          "count": 1,
          "name": "Stark Industries"
        },
        {
          "count": 1,
          "name": "TCRI Building"
        },
        {
          "count": 1,
          "name": "Thriving Bluff"
        },
        {
          "count": 1,
          "name": "Thriving Isle"
        },
        {
          "count": 1,
          "name": "Training Center"
        },
        {
          "count": 1,
          "name": "Vibrant Cityscape"
        },
        {
          "count": 1,
          "name": "Tony Stark"
        }
      ],
      "sideboard": []
    },
    {
      "name": "Krenko, Mob Boss",
      "author": "MTGGoldfish",
      "colors": [
        "R"
      ],
      "tags": [
        "metagame"
      ],
      "main": [
        {
          "count": 1,
          "name": "Krenko, Mob Boss"
        },
        {
          "count": 1,
          "name": "Sunset Strikemaster"
        },
        {
          "count": 1,
          "name": "Zookeeper Mechan"
        },
        {
          "count": 1,
          "name": "Dark-Dweller Oracle"
        },
        {
          "count": 1,
          "name": "Subira, Tulzidi Caravanner"
        },
        {
          "count": 1,
          "name": "Grenzo, Havoc Raiser"
        },
        {
          "count": 1,
          "name": "Goblin Picker"
        },
        {
          "count": 1,
          "name": "Goblin Cratermaker"
        },
        {
          "count": 1,
          "name": "Mogg Mob"
        },
        {
          "count": 1,
          "name": "Gempalm Incinerator"
        },
        {
          "count": 1,
          "name": "Volley Veteran"
        },
        {
          "count": 1,
          "name": "Sarpadian Simulacrum"
        },
        {
          "count": 1,
          "name": "Ember Hauler"
        },
        {
          "count": 1,
          "name": "Arms Dealer"
        },
        {
          "count": 1,
          "name": "Skirk Prospector"
        },
        {
          "count": 1,
          "name": "Reckless Lackey"
        },
        {
          "count": 1,
          "name": "Underfoot Underdogs"
        },
        {
          "count": 1,
          "name": "Goblin Chirurgeon"
        },
        {
          "count": 1,
          "name": "Slash, Reptile Rampager"
        },
        {
          "count": 1,
          "name": "Goblin Motivator"
        },
        {
          "count": 1,
          "name": "Siege-Gang Lieutenant"
        },
        {
          "count": 1,
          "name": "Torch Courier"
        },
        {
          "count": 1,
          "name": "Battle Cry Goblin"
        },
        {
          "count": 1,
          "name": "Ogre Battledriver"
        },
        {
          "count": 1,
          "name": "Mogg War Marshal"
        },
        {
          "count": 1,
          "name": "Legion Warboss"
        },
        {
          "count": 1,
          "name": "Goblin Instigator"
        },
        {
          "count": 1,
          "name": "Witty Roastmaster"
        },
        {
          "count": 1,
          "name": "Beetleback Chief"
        },
        {
          "count": 1,
          "name": "Goblin Matron"
        },
        {
          "count": 1,
          "name": "Siege-Gang Commander"
        },
        {
          "count": 1,
          "name": "Molten Gatekeeper"
        },
        {
          "count": 1,
          "name": "Chaos Warp"
        },
        {
          "count": 1,
          "name": "Goblin Surprise"
        },
        {
          "count": 1,
          "name": "Pack Attack"
        },
        {
          "count": 1,
          "name": "Goblin Wizardry"
        },
        {
          "count": 1,
          "name": "You See a Pair of Goblins"
        },
        {
          "count": 1,
          "name": "Abrade"
        },
        {
          "count": 1,
          "name": "Chain Reaction"
        },
        {
          "count": 1,
          "name": "Ultimate Magic: Meteor"
        },
        {
          "count": 1,
          "name": "Burning Curiosity"
        },
        {
          "count": 1,
          "name": "Krenko's Command"
        },
        {
          "count": 1,
          "name": "Hordeling Outburst"
        },
        {
          "count": 1,
          "name": "Goblin Rally"
        },
        {
          "count": 1,
          "name": "Empty the Warrens"
        },
        {
          "count": 1,
          "name": "Goblin War Party"
        },
        {
          "count": 1,
          "name": "Dragon Fodder"
        },
        {
          "count": 1,
          "name": "Hammer of Purphoros"
        },
        {
          "count": 1,
          "name": "Count on Luck"
        },
        {
          "count": 1,
          "name": "Outpost Siege"
        },
        {
          "count": 1,
          "name": "Goblin Oriflamme"
        },
        {
          "count": 1,
          "name": "Shared Animosity"
        },
        {
          "count": 1,
          "name": "Fire Diamond"
        },
        {
          "count": 1,
          "name": "Heraldic Banner"
        },
        {
          "count": 1,
          "name": "Firdoch Core"
        },
        {
          "count": 1,
          "name": "Everflowing Chalice"
        },
        {
          "count": 1,
          "name": "Commander's Sphere"
        },
        {
          "count": 1,
          "name": "Mind Stone"
        },
        {
          "count": 1,
          "name": "Idol of Oblivion"
        },
        {
          "count": 1,
          "name": "Sol Ring"
        },
        {
          "count": 1,
          "name": "Arcane Signet"
        },
        {
          "count": 1,
          "name": "Sting, the Glinting Dagger"
        },
        {
          "count": 1,
          "name": "Flamekin Village"
        },
        {
          "count": 1,
          "name": "Demolition Field"
        },
        {
          "count": 1,
          "name": "Arch of Orazca"
        },
        {
          "count": 1,
          "name": "Scavenger Grounds"
        },
        {
          "count": 1,
          "name": "Castle Embereth"
        },
        {
          "count": 33,
          "name": "Mountain"
        }
      ],
      "sideboard": []
    },
    {
      "name": "Ultron, Artificial Malevolence",
      "author": "MTGGoldfish",
      "colors": [],
      "tags": [
        "metagame"
      ],
      "main": [
        {
          "count": 1,
          "name": "Ancient Stone Idol"
        },
        {
          "count": 1,
          "name": "Arc Reactor"
        },
        {
          "count": 1,
          "name": "Automated Artificer"
        },
        {
          "count": 1,
          "name": "Buried Ruin"
        },
        {
          "count": 1,
          "name": "Chromatic Star"
        },
        {
          "count": 1,
          "name": "Chrome Dome"
        },
        {
          "count": 1,
          "name": "Cloud Key"
        },
        {
          "count": 1,
          "name": "Conduit Pylons"
        },
        {
          "count": 1,
          "name": "Coveted Jewel"
        },
        {
          "count": 1,
          "name": "Crashing Drawbridge"
        },
        {
          "count": 1,
          "name": "Crystal Grotto"
        },
        {
          "count": 1,
          "name": "Darksteel Citadel"
        },
        {
          "count": 1,
          "name": "Darksteel Colossus"
        },
        {
          "count": 1,
          "name": "Darksteel Ingot"
        },
        {
          "count": 1,
          "name": "Echoes of Eternity"
        },
        {
          "count": 1,
          "name": "Everflowing Chalice"
        },
        {
          "count": 1,
          "name": "Fellwar Stone"
        },
        {
          "count": 1,
          "name": "Foundry Inspector"
        },
        {
          "count": 1,
          "name": "Glaring Fleshraker"
        },
        {
          "count": 1,
          "name": "H.E.R.B.I.E. Scout Unit"
        },
        {
          "count": 1,
          "name": "Hedron Archive"
        },
        {
          "count": 1,
          "name": "Hedron Crawler"
        },
        {
          "count": 1,
          "name": "Helm of Awakening"
        },
        {
          "count": 1,
          "name": "Hidden Grotto"
        },
        {
          "count": 1,
          "name": "Idol of Oblivion"
        },
        {
          "count": 1,
          "name": "It That Heralds the End"
        },
        {
          "count": 1,
          "name": "Jhoira's Familiar"
        },
        {
          "count": 1,
          "name": "Junk Diver"
        },
        {
          "count": 1,
          "name": "Krark-Clan Ironworks"
        },
        {
          "count": 1,
          "name": "Manifold Key"
        },
        {
          "count": 1,
          "name": "Metalwork Colossus"
        },
        {
          "count": 1,
          "name": "Meteor Golem"
        },
        {
          "count": 1,
          "name": "Mind Stone"
        },
        {
          "count": 1,
          "name": "Mind's Eye"
        },
        {
          "count": 1,
          "name": "Myr Battlesphere"
        },
        {
          "count": 1,
          "name": "Mystic Forge"
        },
        {
          "count": 1,
          "name": "Null Elemental Blast"
        },
        {
          "count": 1,
          "name": "Ornithopter of Paradise"
        },
        {
          "count": 1,
          "name": "Palladium Myr"
        },
        {
          "count": 1,
          "name": "Powerstone Shard"
        },
        {
          "count": 1,
          "name": "Prismatic Lens"
        },
        {
          "count": 1,
          "name": "Pristine Talisman"
        },
        {
          "count": 1,
          "name": "Rogue's Passage"
        },
        {
          "count": 1,
          "name": "Scene of the Crime"
        },
        {
          "count": 1,
          "name": "Scrap Trawler"
        },
        {
          "count": 1,
          "name": "Selective Obliteration"
        },
        {
          "count": 1,
          "name": "Shimmer Myr"
        },
        {
          "count": 1,
          "name": "Shrine of the Forsaken Gods"
        },
        {
          "count": 1,
          "name": "Sol Ring"
        },
        {
          "count": 1,
          "name": "Solemn Simulacrum"
        },
        {
          "count": 1,
          "name": "Stonespeaker Crystal"
        },
        {
          "count": 1,
          "name": "Surveillance Room"
        },
        {
          "count": 1,
          "name": "Swiftfoot Boots"
        },
        {
          "count": 1,
          "name": "Temple of the False God"
        },
        {
          "count": 1,
          "name": "Treasure Vault"
        },
        {
          "count": 1,
          "name": "Triplicate Titan"
        },
        {
          "count": 1,
          "name": "Ugin, the Ineffable"
        },
        {
          "count": 1,
          "name": "Ultima, Origin of Oblivion"
        },
        {
          "count": 1,
          "name": "Ultron, Artificial Malevolence"
        },
        {
          "count": 1,
          "name": "Ur-Golem's Eye"
        },
        {
          "count": 1,
          "name": "Urza's Mine"
        },
        {
          "count": 1,
          "name": "Urza's Power Plant"
        },
        {
          "count": 1,
          "name": "Urza's Tower"
        },
        {
          "count": 1,
          "name": "Warping Wail"
        },
        {
          "count": 3,
          "name": "Wastes"
        },
        {
          "count": 1,
          "name": "Worn Powerstone"
        },
        {
          "count": 1,
          "name": "Aang's Journey"
        },
        {
          "count": 1,
          "name": "Artisan of Kozilek"
        },
        {
          "count": 1,
          "name": "Exotic Orchard"
        },
        {
          "count": 1,
          "name": "Secluded Courtyard"
        },
        {
          "count": 1,
          "name": "Spire of Industry"
        },
        {
          "count": 1,
          "name": "Stonecoil Serpent"
        },
        {
          "count": 1,
          "name": "Adventurer's Inn"
        },
        {
          "count": 1,
          "name": "Blast Zone"
        },
        {
          "count": 1,
          "name": "Dreamstone Hedron"
        },
        {
          "count": 1,
          "name": "Drownyard Temple"
        },
        {
          "count": 1,
          "name": "Encroaching Wastes"
        },
        {
          "count": 1,
          "name": "Forge of Heroes"
        },
        {
          "count": 1,
          "name": "Foundry of the Consuls"
        },
        {
          "count": 1,
          "name": "Gilded Lotus"
        },
        {
          "count": 1,
          "name": "Grasping Dunes"
        },
        {
          "count": 1,
          "name": "Nephalia Academy"
        },
        {
          "count": 1,
          "name": "Radiant Fountain"
        },
        {
          "count": 1,
          "name": "Roadside Reliquary"
        },
        {
          "count": 1,
          "name": "Ruins of Oran-Rief"
        },
        {
          "count": 1,
          "name": "Scavenger Grounds"
        },
        {
          "count": 1,
          "name": "Secluded Starforge"
        },
        {
          "count": 1,
          "name": "Zhalfirin Void"
        },
        {
          "count": 1,
          "name": "Demolition Field"
        },
        {
          "count": 1,
          "name": "Moonsilver Key"
        },
        {
          "count": 1,
          "name": "Cogwork Assembler"
        },
        {
          "count": 1,
          "name": "Workshop Assistant"
        },
        {
          "count": 1,
          "name": "Blinkmoth Urn"
        },
        {
          "count": 1,
          "name": "God-Pharaoh's Statue"
        },
        {
          "count": 1,
          "name": "All Is Dust"
        },
        {
          "count": 1,
          "name": "Spine of Ish Sah"
        },
        {
          "count": 1,
          "name": "Ash Barrens"
        },
        {
          "count": 1,
          "name": "Planar Bridge"
        }
      ],
      "sideboard": []
    },
    {
      "name": "Captain America, Team Leader",
      "author": "MTGGoldfish",
      "colors": [
        "U",
        "R",
        "W"
      ],
      "tags": [
        "metagame"
      ],
      "main": [
        {
          "count": 1,
          "name": "Spider-Man, Peter Parker"
        },
        {
          "count": 1,
          "name": "Captain America, Team Leader"
        },
        {
          "count": 1,
          "name": "The Wasp, Winsome Avenger"
        },
        {
          "count": 1,
          "name": "Ant-Man, Elusive Avenger"
        },
        {
          "count": 1,
          "name": "Bastion Protector"
        },
        {
          "count": 1,
          "name": "Black Widow, Agile Avenger"
        },
        {
          "count": 1,
          "name": "Captain America, Super-Soldier"
        },
        {
          "count": 1,
          "name": "Director Nick Fury"
        },
        {
          "count": 1,
          "name": "Falcon and Redwing"
        },
        {
          "count": 1,
          "name": "Jarvis, Earth's Mightiest Butler"
        },
        {
          "count": 1,
          "name": "Jocasta, Automaton Avenger"
        },
        {
          "count": 1,
          "name": "Shang-Chi and the Ten Rings"
        },
        {
          "count": 1,
          "name": "Iron Man, Armored Avenger"
        },
        {
          "count": 1,
          "name": "Iron Man Armor"
        },
        {
          "count": 1,
          "name": "Photon, Mighty Marvel"
        },
        {
          "count": 1,
          "name": "Scarlet Witch, Chaotic Avenger"
        },
        {
          "count": 1,
          "name": "Captain Mar-Vell, Space-Born"
        },
        {
          "count": 1,
          "name": "Hulk, Bruce Banner"
        },
        {
          "count": 1,
          "name": "Quicksilver, Speedster"
        },
        {
          "count": 1,
          "name": "War Machine, Avenging Arsenal"
        },
        {
          "count": 1,
          "name": "Winter Soldier, Reborn Avenger"
        },
        {
          "count": 1,
          "name": "Professor Hulk"
        },
        {
          "count": 1,
          "name": "She-Hulk, Wallbreaker"
        },
        {
          "count": 1,
          "name": "West Coast Expansion"
        },
        {
          "count": 1,
          "name": "Raise the Palisade"
        },
        {
          "count": 1,
          "name": "Destroy Evil"
        },
        {
          "count": 1,
          "name": "Heroic Sacrifice"
        },
        {
          "count": 1,
          "name": "Methods of the Mighty"
        },
        {
          "count": 1,
          "name": "Sol Ring"
        },
        {
          "count": 1,
          "name": "Arcane Signet"
        },
        {
          "count": 1,
          "name": "Fellwar Stone"
        },
        {
          "count": 1,
          "name": "Talisman of Conviction"
        },
        {
          "count": 1,
          "name": "Talisman of Creativity"
        },
        {
          "count": 1,
          "name": "Talisman of Progress"
        },
        {
          "count": 1,
          "name": "Herald's Horn"
        },
        {
          "count": 1,
          "name": "Relic of Legends"
        },
        {
          "count": 1,
          "name": "Door of Destinies"
        },
        {
          "count": 1,
          "name": "Folk Hero"
        },
        {
          "count": 1,
          "name": "Gift of Immortality"
        },
        {
          "count": 1,
          "name": "Reconnaissance Mission"
        },
        {
          "count": 1,
          "name": "Kindred Discovery"
        },
        {
          "count": 1,
          "name": "Avengers Tower"
        },
        {
          "count": 1,
          "name": "Clifftop Retreat"
        },
        {
          "count": 1,
          "name": "Coastal Peak"
        },
        {
          "count": 1,
          "name": "Command Tower"
        },
        {
          "count": 1,
          "name": "Deserted Beach"
        },
        {
          "count": 1,
          "name": "Exotic Orchard"
        },
        {
          "count": 1,
          "name": "Flooded Strand"
        },
        {
          "count": 1,
          "name": "Floodfarm Verge"
        },
        {
          "count": 1,
          "name": "Glacial Fortress"
        },
        {
          "count": 1,
          "name": "Glittering Massif"
        },
        {
          "count": 1,
          "name": "Irrigated Farmland"
        },
        {
          "count": 2,
          "name": "Island"
        },
        {
          "count": 2,
          "name": "Mountain"
        },
        {
          "count": 1,
          "name": "Path of Ancestry"
        },
        {
          "count": 2,
          "name": "Plains"
        },
        {
          "count": 1,
          "name": "Plaza of Heroes"
        },
        {
          "count": 1,
          "name": "Prairie Stream"
        },
        {
          "count": 1,
          "name": "Radiant Summit"
        },
        {
          "count": 1,
          "name": "Raugrin Triome"
        },
        {
          "count": 1,
          "name": "Reflecting Pool"
        },
        {
          "count": 1,
          "name": "Riverpyre Verge"
        },
        {
          "count": 1,
          "name": "Sacred Foundry"
        },
        {
          "count": 1,
          "name": "Scalding Tarn"
        },
        {
          "count": 1,
          "name": "Scorched Geyser"
        },
        {
          "count": 1,
          "name": "Sea of Clouds"
        },
        {
          "count": 1,
          "name": "Secluded Courtyard"
        },
        {
          "count": 1,
          "name": "Spectator Seating"
        },
        {
          "count": 1,
          "name": "Steam Vents"
        },
        {
          "count": 1,
          "name": "Stormcarved Coast"
        },
        {
          "count": 1,
          "name": "Sulfur Falls"
        },
        {
          "count": 1,
          "name": "Sunbillow Verge"
        },
        {
          "count": 1,
          "name": "Sundown Pass"
        },
        {
          "count": 1,
          "name": "Training Center"
        },
        {
          "count": 1,
          "name": "Unclaimed Territory"
        },
        {
          "count": 1,
          "name": "Rip Apart"
        },
        {
          "count": 1,
          "name": "Path to Exile"
        },
        {
          "count": 1,
          "name": "Thought Vessel"
        },
        {
          "count": 1,
          "name": "Biorganic Carapace"
        },
        {
          "count": 1,
          "name": "Ripples of Potential"
        },
        {
          "count": 1,
          "name": "Agent Phil Coulson"
        },
        {
          "count": 1,
          "name": "Akki Battle Squad"
        },
        {
          "count": 1,
          "name": "Arana, Heart of the Spider"
        },
        {
          "count": 1,
          "name": "Avengers Assemble!"
        },
        {
          "count": 1,
          "name": "Captain Marvel, Shooting Star"
        },
        {
          "count": 1,
          "name": "Danny Pink"
        },
        {
          "count": 1,
          "name": "Damning Verdict"
        },
        {
          "count": 1,
          "name": "Daredevil, Man Without Fear"
        },
        {
          "count": 1,
          "name": "Matt Murdock, Justice Seeker"
        },
        {
          "count": 1,
          "name": "Night Nurse, Healer of Heroes"
        },
        {
          "count": 1,
          "name": "Spider-Woman, Stunning Savior"
        },
        {
          "count": 1,
          "name": "Wave Goodbye"
        },
        {
          "count": 1,
          "name": "Captain Marvel, Apex Avenger"
        },
        {
          "count": 1,
          "name": "Hercules, Olympian Hero"
        },
        {
          "count": 1,
          "name": "Rescue, Pepper Potts"
        },
        {
          "count": 1,
          "name": "Swords to Plowshares"
        },
        {
          "count": 1,
          "name": "Thor, God of Thunder"
        }
      ],
      "sideboard": []
    },
    {
      "name": "Arixmethes, Slumbering Isle",
      "author": "MTGGoldfish",
      "colors": [
        "U",
        "G"
      ],
      "tags": [
        "metagame"
      ],
      "main": [
        {
          "count": 1,
          "name": "Colossal Whale"
        },
        {
          "count": 1,
          "name": "Cultivate"
        },
        {
          "count": 1,
          "name": "Ethereal Forager"
        },
        {
          "count": 1,
          "name": "Peregrine Drake"
        },
        {
          "count": 1,
          "name": "Growth Spiral"
        },
        {
          "count": 1,
          "name": "Kiora's Follower"
        },
        {
          "count": 1,
          "name": "Kiora, Behemoth Beckoner"
        },
        {
          "count": 1,
          "name": "Tolarian Kraken"
        },
        {
          "count": 1,
          "name": "Long-Finned Skywhale"
        },
        {
          "count": 1,
          "name": "Phase Dolphin"
        },
        {
          "count": 1,
          "name": "Rampant Growth"
        },
        {
          "count": 1,
          "name": "Scourge of Fleets"
        },
        {
          "count": 1,
          "name": "Slinn Voda, the Rising Deep"
        },
        {
          "count": 1,
          "name": "Shipbreaker Kraken"
        },
        {
          "count": 1,
          "name": "Stormsurge Kraken"
        },
        {
          "count": 1,
          "name": "Waker of Waves"
        },
        {
          "count": 1,
          "name": "Whelming Wave"
        },
        {
          "count": 1,
          "name": "Xolatoyac, the Smiling Flood"
        },
        {
          "count": 1,
          "name": "Arixmethes, Slumbering Isle"
        },
        {
          "count": 1,
          "name": "Dreamtide Whale"
        },
        {
          "count": 1,
          "name": "One With the Wind"
        },
        {
          "count": 1,
          "name": "Wine of Blood and Iron"
        },
        {
          "count": 1,
          "name": "Magus of the Candelabra"
        },
        {
          "count": 1,
          "name": "Wild Growth"
        },
        {
          "count": 1,
          "name": "Mind Stone"
        },
        {
          "count": 1,
          "name": "Arcane Signet"
        },
        {
          "count": 1,
          "name": "Farseek"
        },
        {
          "count": 1,
          "name": "Fertile Ground"
        },
        {
          "count": 1,
          "name": "Man-o'-War"
        },
        {
          "count": 1,
          "name": "Voyaging Satyr"
        },
        {
          "count": 1,
          "name": "Wolfwillow Haven"
        },
        {
          "count": 1,
          "name": "Overgrowth Elemental"
        },
        {
          "count": 1,
          "name": "Elemental Bond"
        },
        {
          "count": 1,
          "name": "Prime Speaker Zegana"
        },
        {
          "count": 1,
          "name": "Hydroid Krasis"
        },
        {
          "count": 1,
          "name": "Finale of Revelation"
        },
        {
          "count": 1,
          "name": "Hunter's Insight"
        },
        {
          "count": 1,
          "name": "Return of the Wildspeaker"
        },
        {
          "count": 1,
          "name": "Snakeskin Veil"
        },
        {
          "count": 1,
          "name": "See the Unwritten"
        },
        {
          "count": 1,
          "name": "Tromokratis"
        },
        {
          "count": 1,
          "name": "Serpent of Yawning Depths"
        },
        {
          "count": 1,
          "name": "Command Tower"
        },
        {
          "count": 1,
          "name": "Exotic Orchard"
        },
        {
          "count": 1,
          "name": "Hinterland Harbor"
        },
        {
          "count": 14,
          "name": "Island"
        },
        {
          "count": 1,
          "name": "Thornwood Falls"
        },
        {
          "count": 1,
          "name": "Tangled Islet"
        },
        {
          "count": 1,
          "name": "Quandrix Campus"
        },
        {
          "count": 1,
          "name": "Temple of Mystery"
        },
        {
          "count": 1,
          "name": "Path of Ancestry"
        },
        {
          "count": 1,
          "name": "Tangled Florahedron"
        },
        {
          "count": 1,
          "name": "Vineglimmer Snarl"
        },
        {
          "count": 1,
          "name": "Simic Growth Chamber"
        },
        {
          "count": 10,
          "name": "Forest"
        },
        {
          "count": 1,
          "name": "Crashing Drawbridge"
        },
        {
          "count": 1,
          "name": "Threats Undetected"
        },
        {
          "count": 1,
          "name": "Mesmerizing Benthid"
        },
        {
          "count": 1,
          "name": "Archetype of Imagination"
        },
        {
          "count": 1,
          "name": "Return to Nature"
        },
        {
          "count": 1,
          "name": "Tale's End"
        },
        {
          "count": 1,
          "name": "Decisive Denial"
        },
        {
          "count": 1,
          "name": "Negate"
        },
        {
          "count": 1,
          "name": "Disdainful Stroke"
        },
        {
          "count": 1,
          "name": "Repudiate // Replicate"
        },
        {
          "count": 1,
          "name": "Aethertide Whale"
        },
        {
          "count": 1,
          "name": "Horned Loch-Whale"
        },
        {
          "count": 1,
          "name": "Steelfin Whale"
        },
        {
          "count": 1,
          "name": "Glaring Spotlight"
        },
        {
          "count": 1,
          "name": "Spell Rupture"
        },
        {
          "count": 1,
          "name": "Artful Dodge"
        },
        {
          "count": 1,
          "name": "Aqueous Form"
        },
        {
          "count": 1,
          "name": "Charix, the Raging Isle"
        },
        {
          "count": 1,
          "name": "Nimbus Swimmer"
        },
        {
          "count": 1,
          "name": "Garruk's Packleader"
        },
        {
          "count": 1,
          "name": "Verdant Haven"
        },
        {
          "count": 1,
          "name": "Forced Adaptation"
        },
        {
          "count": 1,
          "name": "Nissa's Pilgrimage"
        }
      ],
      "sideboard": [
        {
          "count": 1,
          "name": "Star Whale"
        },
        {
          "count": 1,
          "name": "Spawning Kraken"
        },
        {
          "count": 1,
          "name": "Mystic Remora"
        },
        {
          "count": 1,
          "name": "Kiora Bests the Sea God"
        },
        {
          "count": 1,
          "name": "Breaching Leviathan"
        },
        {
          "count": 1,
          "name": "Aesi, Tyrant of Gyre Strait"
        },
        {
          "count": 1,
          "name": "Guard Gomazoa"
        },
        {
          "count": 1,
          "name": "Sharktocrab"
        },
        {
          "count": 1,
          "name": "Voracious Greatshark"
        },
        {
          "count": 1,
          "name": "Shark Typhoon"
        },
        {
          "count": 1,
          "name": "Tui and La, Moon and Ocean"
        },
        {
          "count": 1,
          "name": "Tatyova, Benthic Druid"
        },
        {
          "count": 1,
          "name": "Thought Sponge"
        },
        {
          "count": 1,
          "name": "Chrome Host Seedshark"
        },
        {
          "count": 1,
          "name": "Show and Tell"
        },
        {
          "count": 1,
          "name": "Fountainport"
        },
        {
          "count": 1,
          "name": "Harmonized Trio"
        },
        {
          "count": 1,
          "name": "Fractal Anomaly"
        }
      ]
    },
    {
      "name": "Esika, God of the Tree",
      "author": "MTGGoldfish",
      "colors": [
        "G",
        "B",
        "W",
        "U"
      ],
      "tags": [
        "metagame"
      ],
      "main": [
        {
          "count": 1,
          "name": "Esika, God of the Tree"
        },
        {
          "count": 1,
          "name": "Dovin, Hand of Control"
        },
        {
          "count": 1,
          "name": "Narset Transcendent"
        },
        {
          "count": 1,
          "name": "Teferi, Hero of Dominaria"
        },
        {
          "count": 1,
          "name": "Teferi, Time Raveler"
        },
        {
          "count": 1,
          "name": "Venser, the Sojourner"
        },
        {
          "count": 1,
          "name": "Ashiok, Dream Render"
        },
        {
          "count": 1,
          "name": "Ashiok, Nightmare Muse"
        },
        {
          "count": 1,
          "name": "Ashiok, Nightmare Weaver"
        },
        {
          "count": 1,
          "name": "Angrath, the Flame-Chained"
        },
        {
          "count": 1,
          "name": "Ob Nixilis, the Adversary"
        },
        {
          "count": 1,
          "name": "Ajani, Mentor of Heroes"
        },
        {
          "count": 1,
          "name": "Ajani, Sleeper Agent"
        },
        {
          "count": 1,
          "name": "Baldur's Gate"
        },
        {
          "count": 1,
          "name": "Citadel Gate"
        },
        {
          "count": 1,
          "name": "Cliffgate"
        },
        {
          "count": 1,
          "name": "Gond Gate"
        },
        {
          "count": 1,
          "name": "Black Dragon Gate"
        },
        {
          "count": 1,
          "name": "Sea Gate"
        },
        {
          "count": 1,
          "name": "Manor Gate"
        },
        {
          "count": 1,
          "name": "Gateway Plaza"
        },
        {
          "count": 1,
          "name": "Kaya, Intangible Slayer"
        },
        {
          "count": 1,
          "name": "Kaya the Inexorable"
        },
        {
          "count": 1,
          "name": "Sorin, Grim Nemesis"
        },
        {
          "count": 1,
          "name": "Saheeli, Sublime Artificer"
        },
        {
          "count": 1,
          "name": "Garruk, Apex Predator"
        },
        {
          "count": 1,
          "name": "Vraska, Relic Seeker"
        },
        {
          "count": 1,
          "name": "Quintorius Kand"
        },
        {
          "count": 1,
          "name": "Kasmina, Enigma Sage"
        },
        {
          "count": 1,
          "name": "Kiora, the Crashing Wave"
        },
        {
          "count": 1,
          "name": "Nissa, Steward of Elements"
        },
        {
          "count": 1,
          "name": "Oko, Thief of Crowns"
        },
        {
          "count": 1,
          "name": "Call the Gatewatch"
        },
        {
          "count": 1,
          "name": "Ketria Triome"
        },
        {
          "count": 1,
          "name": "Zagoth Triome"
        },
        {
          "count": 1,
          "name": "Raugrin Triome"
        },
        {
          "count": 1,
          "name": "Supreme Verdict"
        },
        {
          "count": 1,
          "name": "Oath of Teferi"
        },
        {
          "count": 1,
          "name": "Azorius Guildgate"
        },
        {
          "count": 1,
          "name": "Boros Guildgate"
        },
        {
          "count": 1,
          "name": "Dimir Guildgate"
        },
        {
          "count": 1,
          "name": "Golgari Guildgate"
        },
        {
          "count": 1,
          "name": "Gruul Guildgate"
        },
        {
          "count": 1,
          "name": "Izzet Guildgate"
        },
        {
          "count": 1,
          "name": "Maze's End"
        },
        {
          "count": 1,
          "name": "Orzhov Guildgate"
        },
        {
          "count": 1,
          "name": "Rakdos Guildgate"
        },
        {
          "count": 1,
          "name": "Selesnya Guildgate"
        },
        {
          "count": 1,
          "name": "Simic Guildgate"
        },
        {
          "count": 2,
          "name": "Forest"
        },
        {
          "count": 2,
          "name": "Swamp"
        },
        {
          "count": 2,
          "name": "Plains"
        },
        {
          "count": 2,
          "name": "Island"
        },
        {
          "count": 1,
          "name": "The World Tree"
        },
        {
          "count": 1,
          "name": "Spara's Headquarters"
        },
        {
          "count": 1,
          "name": "Temple of Plenty"
        },
        {
          "count": 1,
          "name": "Temple of Malady"
        },
        {
          "count": 1,
          "name": "Heap Gate"
        },
        {
          "count": 1,
          "name": "Temple of Mystery"
        },
        {
          "count": 1,
          "name": "Ziatora's Proving Ground"
        },
        {
          "count": 1,
          "name": "Jetmir's Garden"
        },
        {
          "count": 1,
          "name": "Wrath of God"
        },
        {
          "count": 1,
          "name": "Black Sun's Zenith"
        },
        {
          "count": 1,
          "name": "Blasphemous Edict"
        },
        {
          "count": 1,
          "name": "Rhystic Study"
        },
        {
          "count": 1,
          "name": "Blessed Respite"
        },
        {
          "count": 1,
          "name": "Comeuppance"
        },
        {
          "count": 1,
          "name": "Eerie Interference"
        },
        {
          "count": 1,
          "name": "Arachnogenesis"
        },
        {
          "count": 1,
          "name": "Respite"
        },
        {
          "count": 1,
          "name": "Perch Protection"
        },
        {
          "count": 1,
          "name": "Safe Passage"
        },
        {
          "count": 1,
          "name": "Inkshield"
        },
        {
          "count": 1,
          "name": "Lull"
        },
        {
          "count": 1,
          "name": "Fog"
        },
        {
          "count": 1,
          "name": "Decorum Dissertation"
        },
        {
          "count": 1,
          "name": "Sphinx's Revelation"
        },
        {
          "count": 1,
          "name": "Blue Sun's Zenith"
        },
        {
          "count": 1,
          "name": "Search for Azcanta"
        },
        {
          "count": 1,
          "name": "The Meathook Massacre"
        },
        {
          "count": 1,
          "name": "Phyrexian Arena"
        },
        {
          "count": 1,
          "name": "Hour of Promise"
        },
        {
          "count": 1,
          "name": "Tempt with Discovery"
        },
        {
          "count": 1,
          "name": "Open the Way"
        },
        {
          "count": 1,
          "name": "Riot Control"
        },
        {
          "count": 1,
          "name": "Narset, Parter of Veils"
        },
        {
          "count": 1,
          "name": "Elspeth Tirel"
        },
        {
          "count": 1,
          "name": "The Eternal Wanderer"
        },
        {
          "count": 1,
          "name": "Elspeth, Sun's Champion"
        },
        {
          "count": 1,
          "name": "Teferi, Temporal Pilgrim"
        },
        {
          "count": 1,
          "name": "Tamiyo, the Moon Sage"
        },
        {
          "count": 1,
          "name": "Chandra, Torch of Defiance"
        },
        {
          "count": 1,
          "name": "Garruk, Primal Hunter"
        },
        {
          "count": 1,
          "name": "Karn Liberated"
        },
        {
          "count": 1,
          "name": "Nicol Bolas, Dragon-God"
        },
        {
          "count": 1,
          "name": "Jace, Memory Adept"
        }
      ],
      "sideboard": []
    },
    {
      "name": "Edgar Markov",
      "author": "MTGGoldfish",
      "colors": [
        "R",
        "W",
        "B"
      ],
      "tags": [
        "metagame"
      ],
      "main": [
        {
          "count": 1,
          "name": "Accursed Duneyard"
        },
        {
          "count": 1,
          "name": "Axgard Armory"
        },
        {
          "count": 1,
          "name": "Blackcleave Cliffs"
        },
        {
          "count": 1,
          "name": "Clifftop Retreat"
        },
        {
          "count": 1,
          "name": "Command Tower"
        },
        {
          "count": 1,
          "name": "Concealed Courtyard"
        },
        {
          "count": 1,
          "name": "Dragonskull Summit"
        },
        {
          "count": 1,
          "name": "Evolving Wilds"
        },
        {
          "count": 1,
          "name": "Foreboding Ruins"
        },
        {
          "count": 1,
          "name": "Furycalm Snarl"
        },
        {
          "count": 1,
          "name": "Inspiring Vantage"
        },
        {
          "count": 1,
          "name": "Isolated Chapel"
        },
        {
          "count": 1,
          "name": "Mountain"
        },
        {
          "count": 1,
          "name": "Nomad Outpost"
        },
        {
          "count": 1,
          "name": "Path of Ancestry"
        },
        {
          "count": 2,
          "name": "Plains"
        },
        {
          "count": 1,
          "name": "Secluded Courtyard"
        },
        {
          "count": 1,
          "name": "Shattered Landscape"
        },
        {
          "count": 1,
          "name": "Shineshadow Snarl"
        },
        {
          "count": 1,
          "name": "Smoldering Marsh"
        },
        {
          "count": 5,
          "name": "Swamp"
        },
        {
          "count": 1,
          "name": "Temple of Malice"
        },
        {
          "count": 1,
          "name": "Temple of Silence"
        },
        {
          "count": 1,
          "name": "Temple of Triumph"
        },
        {
          "count": 1,
          "name": "Temple of the False God"
        },
        {
          "count": 1,
          "name": "Terramorphic Expanse"
        },
        {
          "count": 1,
          "name": "Unclaimed Territory"
        },
        {
          "count": 1,
          "name": "Vault of the Archangel"
        },
        {
          "count": 1,
          "name": "Voldaren Estate"
        },
        {
          "count": 1,
          "name": "Sorin, Imperious Bloodlord"
        },
        {
          "count": 1,
          "name": "Sorin, Lord of Innistrad"
        },
        {
          "count": 1,
          "name": "Arcane Signet"
        },
        {
          "count": 1,
          "name": "Blade of the Bloodchief"
        },
        {
          "count": 1,
          "name": "Boros Signet"
        },
        {
          "count": 1,
          "name": "Lightning Greaves"
        },
        {
          "count": 1,
          "name": "Orzhov Signet"
        },
        {
          "count": 1,
          "name": "Rakdos Signet"
        },
        {
          "count": 1,
          "name": "Skullclamp"
        },
        {
          "count": 1,
          "name": "Sol Ring"
        },
        {
          "count": 1,
          "name": "Swiftfoot Boots"
        },
        {
          "count": 1,
          "name": "All-Out Assault"
        },
        {
          "count": 1,
          "name": "Phyrexian Arena"
        },
        {
          "count": 1,
          "name": "Sanguine Bond"
        },
        {
          "count": 1,
          "name": "Shared Animosity"
        },
        {
          "count": 1,
          "name": "Stensia Masquerade"
        },
        {
          "count": 1,
          "name": "Damn"
        },
        {
          "count": 1,
          "name": "Diabolic Tutor"
        },
        {
          "count": 1,
          "name": "Gamble"
        },
        {
          "count": 1,
          "name": "New Blood"
        },
        {
          "count": 1,
          "name": "Olivia's Wrath"
        },
        {
          "count": 1,
          "name": "Pact of the Serpent"
        },
        {
          "count": 1,
          "name": "Vindicate"
        },
        {
          "count": 1,
          "name": "Anguished Unmaking"
        },
        {
          "count": 1,
          "name": "Deadly Dispute"
        },
        {
          "count": 1,
          "name": "Mortify"
        },
        {
          "count": 1,
          "name": "Return to Dust"
        },
        {
          "count": 1,
          "name": "Swords to Plowshares"
        },
        {
          "count": 1,
          "name": "Terminate"
        },
        {
          "count": 1,
          "name": "Tragic Slip"
        },
        {
          "count": 1,
          "name": "Village Rites"
        },
        {
          "count": 1,
          "name": "Anowon, the Ruin Sage"
        },
        {
          "count": 1,
          "name": "Blood Artist"
        },
        {
          "count": 1,
          "name": "Bloodline Keeper"
        },
        {
          "count": 1,
          "name": "Bloodlord of Vaasgoth"
        },
        {
          "count": 1,
          "name": "Butcher of Malakir"
        },
        {
          "count": 1,
          "name": "Captivating Vampire"
        },
        {
          "count": 1,
          "name": "Champion of Dusk"
        },
        {
          "count": 1,
          "name": "Clavileno, First of the Blessed"
        },
        {
          "count": 1,
          "name": "Cordial Vampire"
        },
        {
          "count": 1,
          "name": "Crossway Troublemakers"
        },
        {
          "count": 1,
          "name": "Cruel Celebrant"
        },
        {
          "count": 1,
          "name": "Drana, Liberator of Malakir"
        },
        {
          "count": 1,
          "name": "Edgar, Charmed Groom"
        },
        {
          "count": 1,
          "name": "Elenda, the Dusk Rose"
        },
        {
          "count": 1,
          "name": "Forerunner of the Legion"
        },
        {
          "count": 1,
          "name": "Indulgent Aristocrat"
        },
        {
          "count": 1,
          "name": "Kalastria Highborn"
        },
        {
          "count": 1,
          "name": "Knight of the Ebon Legion"
        },
        {
          "count": 1,
          "name": "Legion Lieutenant"
        },
        {
          "count": 1,
          "name": "Malakir Bloodwitch"
        },
        {
          "count": 1,
          "name": "Markov Baron"
        },
        {
          "count": 1,
          "name": "Mavren Fein, Dusk Apostle"
        },
        {
          "count": 1,
          "name": "Olivia, Crimson Bride"
        },
        {
          "count": 1,
          "name": "Patron of the Vein"
        },
        {
          "count": 1,
          "name": "Preacher of the Schism"
        },
        {
          "count": 1,
          "name": "Rakish Heir"
        },
        {
          "count": 1,
          "name": "Sanctum Seeker"
        },
        {
          "count": 1,
          "name": "Stromkirk Captain"
        },
        {
          "count": 1,
          "name": "Twilight Prophet"
        },
        {
          "count": 1,
          "name": "Vampire Socialite"
        },
        {
          "count": 1,
          "name": "Viscera Seer"
        },
        {
          "count": 1,
          "name": "Vito, Thorn of the Dusk Rose"
        },
        {
          "count": 1,
          "name": "Welcoming Vampire"
        },
        {
          "count": 1,
          "name": "Yahenni, Undying Partisan"
        },
        {
          "count": 1,
          "name": "Edgar Markov"
        }
      ],
      "sideboard": []
    }
  ]
}